AjayPackage/__init__.py
AjayPackage/functions.py
AjayPackage/greet.py
AjayPackage-0.1.dist-info/METADATA
AjayPackage-0.1.dist-info/WHEEL
AjayPackage-0.1.dist-info/top_level.txt
AjayPackage-0.1.dist-info/RECORD
