Metadata-Version: 2.1
Name: AjayPackage
Version: 0.1
Summary: Testing installation of Package
Home-page: 
Author: Ajay Patil
Author-email: ajaypatil.nmu@gmail.com
License: MIT
